MANIFEST.in
README.rst
setup.py
hidden_markov/__init__.py
hidden_markov/hmm_class.py
hidden_markov.egg-info/PKG-INFO
hidden_markov.egg-info/SOURCES.txt
hidden_markov.egg-info/dependency_links.txt
hidden_markov.egg-info/not-zip-safe
hidden_markov.egg-info/requires.txt
hidden_markov.egg-info/top_level.txt