Metadata-Version: 1.1
Name: hidden-markov
Version: 0.3.2
Summary: Implementation of Hidden markov model in discrete domain.
Home-page: http://github.com/Red-devilz/hidden_markov
Author: Rahul
Author-email: UNKNOWN
License: MIT
Keywords: hmm hidden markov model
Platform: UNKNOWN
Classifier: Development Status :: 3 - Alpha
Classifier: Programming Language :: Python :: 2.7
Classifier: Programming Language :: Python :: 3.4
Classifier: Programming Language :: Python :: 3.5
